<?xml version="1.0" encoding="UTF-8"?>
<!--
 - Copyright 1999-2011 Alibaba Group.
 -
 - Licensed under the Apache License, Version 2.0 (the "License");
 - you may not use this file except in compliance with the License.
 - You may obtain a copy of the License at
 -
 -      http://www.apache.org/licenses/LICENSE-2.0
 -
 - Unless required by applicable law or agreed to in writing, software
 - distributed under the License is distributed on an "AS IS" BASIS,
 - WITHOUT WARRANTIES OR CONDITIONS OF ANY KIND, either express or implied.
 - See the License for the specific language governing permissions and
 - limitations under the License.
-->
<beans xmlns="http://www.springframework.org/schema/beans"
       xmlns:xsi="http://www.w3.org/2001/XMLSchema-instance"
       xmlns:dubbo="http://code.alibabatech.com/schema/dubbo"
       xsi:schemaLocation="http://www.springframework.org/schema/beans http://www.springframework.org/schema/beans/spring-beans-3.2.xsd
	http://code.alibabatech.com/schema/dubbo http://code.alibabatech.com/schema/dubbo/dubbo.xsd">

    <!--uncomment this if you want to test dubbo's monitor-->
    <dubbo:monitor protocol="registry"/>

    <!-- here we demonstrate both annotation-based and xml-based configs -->
    <dubbo:annotation package="com.fionapet.business.facade"/>

    <!-- use tomcat server -->
    <dubbo:protocol name="rest" threads="500" contextpath="api/v2" server="tomcat" accepts="500"
                    extension="com.fionapet.business.extension.TraceInterceptor,
                    com.fionapet.business.extension.TraceFilter,
                    com.fionapet.business.extension.ClientTraceFilter,
                    com.fionapet.business.extension.DynamicTraceBinding,
                    com.fionapet.business.extension.CustomExceptionMapper,
                    com.alibaba.dubbo.rpc.protocol.rest.support.LoggingFilter"/>


    <!-- pet race api -->
    <dubbo:service interface="com.fionapet.business.facade.PetRaceRestService" ref="petRaceRestService"
                   protocol="rest" validation="true" timeout="2000" connections="100"/>

    <bean id="petRaceRestService" class="com.fionapet.business.facade.PetRaceRestServiceImpl">
        <property name="petRaceService" ref="petRaceService"/>
    </bean>

    <dubbo:reference id="petRaceService" interface="com.fionapet.business.service.PetRaceService"/>

    <dubbo:service interface="com.fionapet.business.facade.PetSmallRaceRestService" ref="petSmallRaceRestService"
                   protocol="rest" validation="true" timeout="2000" connections="100"/>

    <bean id="petSmallRaceRestService" class="com.fionapet.business.facade.PetSmallRaceRestServiceImpl">
        <property name="petSmallRaceService" ref="petSmallRaceService"/>
    </bean>

    <dubbo:reference id="petSmallRaceService" interface="com.fionapet.business.service.PetSmallRaceService"/>
    <!-- pet race api -->

    <dubbo:reference id="accountService" interface="cn.fiona.pet.account.service.AccountService"/>

    <!--warehouse api -->
    <dubbo:service interface="com.fionapet.business.facade.WarehouseRestService" ref="warehouseRestService"
                   protocol="rest" validation="true" timeout="2000" connections="100"/>

    <bean id="warehouseRestService" class="com.fionapet.business.facade.WarehouseRestServiceImpl">
        <property name="warehouseService" ref="warehouseService"/>
    </bean>

    <dubbo:reference id="warehouseService" interface="com.fionapet.business.service.WarehouseService"/>

    <!-- warehouse api-->
    <!--itemcate api -->
    <dubbo:service interface="com.fionapet.business.facade.ItemCateRestService" ref="itemCateRestService"
                   protocol="rest" validation="true" timeout="2000" connections="100"/>

    <bean id="itemCateRestService" class="com.fionapet.business.facade.ItemCateRestServiceImpl">
        <property name="itemCateService" ref="itemCateService"/>
    </bean>

    <dubbo:reference id="itemCateService" interface="com.fionapet.business.service.ItemCateService"/>

    <!-- itemcate api-->
    <!--businesCate api -->
    <dubbo:service interface="com.fionapet.business.facade.BusinesCateRestService" ref="businesCateRestService"
                   protocol="rest" validation="true" timeout="2000" connections="100"/>

    <bean id="businesCateRestService" class="com.fionapet.business.facade.BusinesCateRestServiceImpl">
        <property name="businesCateService" ref="businesCateService"/>
    </bean>

    <dubbo:reference id="businesCateService" interface="com.fionapet.business.service.BusinesCateService"/>

    <!-- businesCate api-->

	<!--经销商 api -->
    <dubbo:service interface="com.fionapet.business.facade.DealerRestService" ref="dealerRestService"
                   protocol="rest" validation="true" timeout="2000" connections="100"/>

    <bean id="dealerRestService" class="com.fionapet.business.facade.DealerRestServiceImpl">
        <property name="dealerService" ref="dealerService"/>
    </bean>

    <dubbo:reference id="dealerService" interface="com.fionapet.business.service.DealerService"/>
    <!--经销商 api -->


	<!--商品和服务类型 api -->
    <dubbo:service interface="com.fionapet.business.facade.ItemTypeRestService" ref="itemTypeRestService"
                   protocol="rest" validation="true" timeout="2000" connections="100"/>

    <bean id="itemTypeRestService" class="com.fionapet.business.facade.ItemTypeRestServiceImpl">
        <property name="itemTypeService" ref="itemTypeService"/>
    </bean>

    <dubbo:reference id="itemTypeService" interface="com.fionapet.business.service.ItemTypeService"/>
    <!--商品和服务类型 api -->


	<!--应用配置 api -->
    <dubbo:service interface="com.fionapet.business.facade.AppConfigRestService" ref="appConfigRestService"
                   protocol="rest" validation="true" timeout="2000" connections="100"/>

    <bean id="appConfigRestService" class="com.fionapet.business.facade.AppConfigRestServiceImpl">
        <property name="appConfigService" ref="appConfigService"/>
    </bean>

    <dubbo:reference id="appConfigService" interface="com.fionapet.business..service.AppConfigService"/>
    <!--应用配置 api -->


	<!--电话信息表 api -->
    <dubbo:service interface="com.fionapet.business.facade.PhoneMessageRestService" ref="phoneMessageRestService"
                   protocol="rest" validation="true" timeout="2000" connections="100"/>

    <bean id="phoneMessageRestService" class="com.fionapet.business.facade.PhoneMessageRestServiceImpl">
        <property name="phoneMessageService" ref="phoneMessageService"/>
    </bean>

    <dubbo:reference id="phoneMessageService" interface="com.fionapet.business.service.PhoneMessageService"/>
    <!--电话信息表 api -->


	<!--移库记录 api -->
    <dubbo:service interface="com.fionapet.business.facade.WarehouseMoverecordRestService" ref="warehouseMoverecordRestService"
                   protocol="rest" validation="true" timeout="2000" connections="100"/>

    <bean id="warehouseMoverecordRestService" class="com.fionapet.business.facade.WarehouseMoverecordRestServiceImpl">
        <property name="warehouseMoverecordService" ref="warehouseMoverecordService"/>
    </bean>

    <dubbo:reference id="warehouseMoverecordService" interface="com.fionapet.business.service.WarehouseMoverecordService"/>
    <!--移库记录 api -->


	<!--仓库存货清单 api -->
    <dubbo:service interface="com.fionapet.business.facade.WarehouseInventoryRestService" ref="warehouseInventoryRestService"
                   protocol="rest" validation="true" timeout="2000" connections="100"/>

    <bean id="warehouseInventoryRestService" class="com.fionapet.business.facade.WarehouseInventoryRestServiceImpl">
        <property name="warehouseInventoryService" ref="warehouseInventoryService"/>
    </bean>

    <dubbo:reference id="warehouseInventoryService" interface="com.fionapet.business.service.WarehouseInventoryService"/>
    <!--仓库存货清单 api -->


	<!--医生化验实例类型细节表 api -->
    <dubbo:service interface="com.fionapet.business.facade.MedicChemicalExamtypeDetailRestService" ref="medicChemicalExamtypeDetailRestService"
                   protocol="rest" validation="true" timeout="2000" connections="100"/>

    <bean id="medicChemicalExamtypeDetailRestService" class="com.fionapet.business.facade.MedicChemicalExamtypeDetailRestServiceImpl">
        <property name="medicChemicalExamtypeDetailService" ref="medicChemicalExamtypeDetailService"/>
    </bean>

    <dubbo:reference id="medicChemicalExamtypeDetailService" interface="com.fionapet.business.service.MedicChemicalExamtypeDetailService"/>
    <!--医生化验实例类型细节表 api -->


	<!--退回记录 api -->
    <dubbo:service interface="com.fionapet.business.facade.WarehouseBackrecordRestService" ref="warehouseBackrecordRestService"
                   protocol="rest" validation="true" timeout="2000" connections="100"/>

    <bean id="warehouseBackrecordRestService" class="com.fionapet.business.facade.WarehouseBackrecordRestServiceImpl">
        <property name="warehouseBackrecordService" ref="warehouseBackrecordService"/>
    </bean>

    <dubbo:reference id="warehouseBackrecordService" interface="com.fionapet.business.service.WarehouseBackrecordService"/>
    <!--退回记录 api -->


	<!--仓库直销主表 api -->
    <dubbo:service interface="com.fionapet.business.facade.StoreDirectSellRestService" ref="storeDirectSellRestService"
                   protocol="rest" validation="true" timeout="2000" connections="100"/>

    <bean id="storeDirectSellRestService" class="com.fionapet.business.facade.StoreDirectSellRestServiceImpl">
        <property name="storeDirectSellService" ref="storeDirectSellService"/>
    </bean>

    <dubbo:reference id="storeDirectSellService" interface="com.fionapet.business.service.StoreDirectSellService"/>
    <!--仓库直销主表 api -->


	<!--育苗表 api -->
    <dubbo:service interface="com.fionapet.business.facade.MedicVaccineRestService" ref="medicVaccineRestService"
                   protocol="rest" validation="true" timeout="2000" connections="100"/>

    <bean id="medicVaccineRestService" class="com.fionapet.business.facade.MedicVaccineRestServiceImpl">
        <property name="medicVaccineService" ref="medicVaccineService"/>
    </bean>

    <dubbo:reference id="medicVaccineService" interface="com.fionapet.business.service.MedicVaccineService"/>
    <!--育苗表 api -->


	<!--医生处方明细 api -->
    <dubbo:service interface="com.fionapet.business.facade.MedicPrescriptionRestService" ref="medicPrescriptionRestService"
                   protocol="rest" validation="true" timeout="2000" connections="100"/>

    <bean id="medicPrescriptionRestService" class="com.fionapet.business.facade.MedicPrescriptionRestServiceImpl">
        <property name="medicPrescriptionService" ref="medicPrescriptionService"/>
    </bean>

    <dubbo:reference id="medicPrescriptionService" interface="com.fionapet.business.service.MedicPrescriptionService"/>
    <!--医生处方明细 api -->


	<!--医生供应量表 api -->
    <dubbo:service interface="com.fionapet.business.facade.MedicSuppliesRestService" ref="medicSuppliesRestService"
                   protocol="rest" validation="true" timeout="2000" connections="100"/>

    <bean id="medicSuppliesRestService" class="com.fionapet.business.facade.MedicSuppliesRestServiceImpl">
        <property name="medicSuppliesService" ref="medicSuppliesService"/>
    </bean>

    <dubbo:reference id="medicSuppliesService" interface="com.fionapet.business.service.MedicSuppliesService"/>
    <!--医生供应量表 api -->


	<!--序列号 api -->
    <dubbo:service interface="com.fionapet.business.facade.RewardPointLogRestService" ref="rewardPointLogRestService"
                   protocol="rest" validation="true" timeout="2000" connections="100"/>

    <bean id="rewardPointLogRestService" class="com.fionapet.business.facade.RewardPointLogRestServiceImpl">
        <property name="rewardPointLogService" ref="rewardPointLogService"/>
    </bean>

    <dubbo:reference id="rewardPointLogService" interface="com.fionapet.business.service.RewardPointLogService"/>
    <!--序列号 api -->


	<!--退回记录明细 api -->
    <dubbo:service interface="com.fionapet.business.facade.WarehouseBackrecordDetailRestService" ref="warehouseBackrecordDetailRestService"
                   protocol="rest" validation="true" timeout="2000" connections="100"/>

    <bean id="warehouseBackrecordDetailRestService" class="com.fionapet.business.facade.WarehouseBackrecordDetailRestServiceImpl">
        <property name="warehouseBackrecordDetailService" ref="warehouseBackrecordDetailService"/>
    </bean>

    <dubbo:reference id="warehouseBackrecordDetailService" interface="com.fionapet.business.service.WarehouseBackrecordDetailService"/>
    <!--退回记录明细 api -->


	<!--返回商品主表 api -->
    <dubbo:service interface="com.fionapet.business.facade.ReturnCommodityRestService" ref="returnCommodityRestService"
                   protocol="rest" validation="true" timeout="2000" connections="100"/>

    <bean id="returnCommodityRestService" class="com.fionapet.business.facade.ReturnCommodityRestServiceImpl">
        <property name="returnCommodityService" ref="returnCommodityService"/>
    </bean>

    <dubbo:reference id="returnCommodityService" interface="com.fionapet.business.service.ReturnCommodityService"/>
    <!--返回商品主表 api -->


	<!--医生处方明细 api -->
    <dubbo:service interface="com.fionapet.business.facade.MedicPrescriptionDetailRestService" ref="medicPrescriptionDetailRestService"
                   protocol="rest" validation="true" timeout="2000" connections="100"/>

    <bean id="medicPrescriptionDetailRestService" class="com.fionapet.business.facade.MedicPrescriptionDetailRestServiceImpl">
        <property name="medicPrescriptionDetailService" ref="medicPrescriptionDetailService"/>
    </bean>

    <dubbo:reference id="medicPrescriptionDetailService" interface="com.fionapet.business.service.MedicPrescriptionDetailService"/>
    <!--医生处方明细 api -->


	<!--消息提醒配置表 api -->
    <dubbo:service interface="com.fionapet.business.facade.MicroSmsConfigRestService" ref="microSmsConfigRestService"
                   protocol="rest" validation="true" timeout="2000" connections="100"/>

    <bean id="microSmsConfigRestService" class="com.fionapet.business.facade.MicroSmsConfigRestServiceImpl">
        <property name="microSmsConfigService" ref="microSmsConfigService"/>
    </bean>

    <dubbo:reference id="microSmsConfigService" interface="com.fionapet.business.service.MicroSmsConfigService"/>
    <!--消息提醒配置表 api -->


	<!--进库记录 api -->
    <dubbo:service interface="com.fionapet.business.facade.WarehouseInrecordRestService" ref="warehouseInrecordRestService"
                   protocol="rest" validation="true" timeout="2000" connections="100"/>

    <bean id="warehouseInrecordRestService" class="com.fionapet.business.facade.WarehouseInrecordRestServiceImpl">
        <property name="warehouseInrecordService" ref="warehouseInrecordService"/>
    </bean>

    <dubbo:reference id="warehouseInrecordService" interface="com.fionapet.business.service.WarehouseInrecordService"/>
    <!--进库记录 api -->


	<!--医生登记记录明细 api -->
    <dubbo:service interface="com.fionapet.business.facade.MedicRegisterRecordRestService" ref="medicRegisterRecordRestService"
                   protocol="rest" validation="true" timeout="2000" connections="100"/>

    <bean id="medicRegisterRecordRestService" class="com.fionapet.business.facade.MedicRegisterRecordRestServiceImpl">
        <property name="medicRegisterRecordService" ref="medicRegisterRecordService"/>
    </bean>

    <dubbo:reference id="medicRegisterRecordService" interface="com.fionapet.business.service.MedicRegisterRecordService"/>
    <!--医生登记记录明细 api -->


	<!--提前付费表 api -->
    <dubbo:service interface="com.fionapet.business.facade.PrepayMoneyRestService" ref="prepayMoneyRestService"
                   protocol="rest" validation="true" timeout="2000" connections="100"/>

    <bean id="prepayMoneyRestService" class="com.fionapet.business.facade.PrepayMoneyRestServiceImpl">
        <property name="prepayMoneyService" ref="prepayMoneyService"/>
    </bean>

    <dubbo:reference id="prepayMoneyService" interface="com.fionapet.business.service.PrepayMoneyService"/>
    <!--提前付费表 api -->


	<!--进库记录明细 api -->
    <dubbo:service interface="com.fionapet.business.facade.WarehouseInrecordDetailRestService" ref="warehouseInrecordDetailRestService"
                   protocol="rest" validation="true" timeout="2000" connections="100"/>

    <bean id="warehouseInrecordDetailRestService" class="com.fionapet.business.facade.WarehouseInrecordDetailRestServiceImpl">
        <property name="warehouseInrecordDetailService" ref="warehouseInrecordDetailService"/>
    </bean>

    <dubbo:reference id="warehouseInrecordDetailService" interface="com.fionapet.business.service.WarehouseInrecordDetailService"/>
    <!--进库记录明细 api -->


	<!--急诊表 api -->
    <dubbo:service interface="com.fionapet.business.facade.PromptRestService" ref="promptRestService"
                   protocol="rest" validation="true" timeout="2000" connections="100"/>

    <bean id="promptRestService" class="com.fionapet.business.facade.PromptRestServiceImpl">
        <property name="promptService" ref="promptService"/>
    </bean>

    <dubbo:reference id="promptService" interface="com.fionapet.business.service.PromptService"/>
    <!--急诊表 api -->


	<!--服务明细 api -->
    <dubbo:service interface="com.fionapet.business.facade.ServiceDetailRestService" ref="serviceDetailRestService"
                   protocol="rest" validation="true" timeout="2000" connections="100"/>

    <bean id="serviceDetailRestService" class="com.fionapet.business.facade.ServiceDetailRestServiceImpl">
        <property name="serviceDetailService" ref="serviceDetailService"/>
    </bean>

    <dubbo:reference id="serviceDetailService" interface="com.fionapet.business.service.ServiceDetailService"/>
    <!--服务明细 api -->


	<!--检查处理单据 api -->
    <dubbo:service interface="com.fionapet.business.facade.CheckProcessSheetRestService" ref="checkProcessSheetRestService"
                   protocol="rest" validation="true" timeout="2000" connections="100"/>

    <bean id="checkProcessSheetRestService" class="com.fionapet.business.facade.CheckProcessSheetRestServiceImpl">
        <property name="checkProcessSheetService" ref="checkProcessSheetService"/>
    </bean>

    <dubbo:reference id="checkProcessSheetService" interface="com.fionapet.business.service.CheckProcessSheetService"/>
    <!--检查处理单据 api -->


	<!--出库记录 api -->
    <dubbo:service interface="com.fionapet.business.facade.WarehouseOutrecordRestService" ref="warehouseOutrecordRestService"
                   protocol="rest" validation="true" timeout="2000" connections="100"/>

    <bean id="warehouseOutrecordRestService" class="com.fionapet.business.facade.WarehouseOutrecordRestServiceImpl">
        <property name="warehouseOutrecordService" ref="warehouseOutrecordService"/>
    </bean>

    <dubbo:reference id="warehouseOutrecordService" interface="com.fionapet.business.service.WarehouseOutrecordService"/>
    <!--出库记录 api -->


	<!--医生化验实例类型细节表 api -->
    <dubbo:service interface="com.fionapet.business.facade.MedicChemicalExamtypeRestService" ref="medicChemicalExamtypeRestService"
                   protocol="rest" validation="true" timeout="2000" connections="100"/>

    <bean id="medicChemicalExamtypeRestService" class="com.fionapet.business.facade.MedicChemicalExamtypeRestServiceImpl">
        <property name="medicChemicalExamtypeService" ref="medicChemicalExamtypeService"/>
    </bean>

    <dubbo:reference id="medicChemicalExamtypeService" interface="com.fionapet.business.service.MedicChemicalExamtypeService"/>
    <!--医生化验实例类型细节表 api -->


	<!--医生处理记录 api -->
    <dubbo:service interface="com.fionapet.business.facade.MedicMedictreatRecordRestService" ref="medicMedictreatRecordRestService"
                   protocol="rest" validation="true" timeout="2000" connections="100"/>

    <bean id="medicMedictreatRecordRestService" class="com.fionapet.business.facade.MedicMedictreatRecordRestServiceImpl">
        <property name="medicMedictreatRecordService" ref="medicMedictreatRecordService"/>
    </bean>

    <dubbo:reference id="medicMedictreatRecordService" interface="com.fionapet.business.service.MedicMedictreatRecordService"/>
    <!--医生处理记录 api -->


	<!--赔偿交换细节 api -->
    <dubbo:service interface="com.fionapet.business.facade.RewardpointExchangeDetailRestService" ref="rewardpointExchangeDetailRestService"
                   protocol="rest" validation="true" timeout="2000" connections="100"/>

    <bean id="rewardpointExchangeDetailRestService" class="com.fionapet.business.facade.RewardpointExchangeDetailRestServiceImpl">
        <property name="rewardpointExchangeDetailService" ref="rewardpointExchangeDetailService"/>
    </bean>

    <dubbo:reference id="rewardpointExchangeDetailService" interface="com.fionapet.business.service.RewardpointExchangeDetailService"/>
    <!--赔偿交换细节 api -->


	<!--出库记录明细 api -->
    <dubbo:service interface="com.fionapet.business.facade.WarehouseOutrecordDetailRestService" ref="warehouseOutrecordDetailRestService"
                   protocol="rest" validation="true" timeout="2000" connections="100"/>

    <bean id="warehouseOutrecordDetailRestService" class="com.fionapet.business.facade.WarehouseOutrecordDetailRestServiceImpl">
        <property name="warehouseOutrecordDetailService" ref="warehouseOutrecordDetailService"/>
    </bean>

    <dubbo:reference id="warehouseOutrecordDetailService" interface="com.fionapet.business.service.WarehouseOutrecordDetailService"/>
    <!--出库记录明细 api -->


	<!--赔偿交换 api -->
    <dubbo:service interface="com.fionapet.business.facade.RewardpointExchangeRestService" ref="rewardpointExchangeRestService"
                   protocol="rest" validation="true" timeout="2000" connections="100"/>

    <bean id="rewardpointExchangeRestService" class="com.fionapet.business.facade.RewardpointExchangeRestServiceImpl">
        <property name="rewardpointExchangeService" ref="rewardpointExchangeService"/>
    </bean>

    <dubbo:reference id="rewardpointExchangeService" interface="com.fionapet.business.service.RewardpointExchangeService"/>
    <!--赔偿交换 api -->


	<!--序列号 api -->
    <dubbo:service interface="com.fionapet.business.facade.SerialNumberRestService" ref="serialNumberRestService"
                   protocol="rest" validation="true" timeout="2000" connections="100"/>

    <bean id="serialNumberRestService" class="com.fionapet.business.facade.SerialNumberRestServiceImpl">
        <property name="serialNumberService" ref="serialNumberService"/>
    </bean>

    <dubbo:reference id="serialNumberService" interface="com.fionapet.business.service.SerialNumberService"/>
    <!--序列号 api -->


	<!--VIP信息 api -->
    <dubbo:service interface="com.fionapet.business.facade.VipInputTemRestService" ref="vipInputTemRestService"
                   protocol="rest" validation="true" timeout="2000" connections="100"/>

    <bean id="vipInputTemRestService" class="com.fionapet.business.facade.VipInputTemRestServiceImpl">
        <property name="vipInputTemService" ref="vipInputTemService"/>
    </bean>

    <dubbo:reference id="vipInputTemService" interface="com.fionapet.business.service.VipInputTemService"/>
    <!--VIP信息 api -->


	<!--审批状态实体 api -->
    <dubbo:service interface="com.fionapet.business.facade.ApproveStatusEntityRestService" ref="approveStatusEntityRestService"
                   protocol="rest" validation="true" timeout="2000" connections="100"/>

    <bean id="approveStatusEntityRestService" class="com.fionapet.business.facade.ApproveStatusEntityRestServiceImpl">
        <property name="approveStatusEntityService" ref="approveStatusEntityService"/>
    </bean>

    <dubbo:reference id="approveStatusEntityService" interface="com.fionapet.business.service.ApproveStatusEntityService"/>
    <!--审批状态实体 api -->


	<!--移库记录明细 api -->
    <dubbo:service interface="com.fionapet.business.facade.WarehouseMoverecordDetailRestService" ref="warehouseMoverecordDetailRestService"
                   protocol="rest" validation="true" timeout="2000" connections="100"/>

    <bean id="warehouseMoverecordDetailRestService" class="com.fionapet.business.facade.WarehouseMoverecordDetailRestServiceImpl">
        <property name="warehouseMoverecordDetailService" ref="warehouseMoverecordDetailService"/>
    </bean>

    <dubbo:reference id="warehouseMoverecordDetailService" interface="com.fionapet.business.service.WarehouseMoverecordDetailService"/>
    <!--移库记录明细 api -->


	<!--仓库直销明细 api -->
    <dubbo:service interface="com.fionapet.business.facade.StoreDirectSellDetailRestService" ref="storeDirectSellDetailRestService"
                   protocol="rest" validation="true" timeout="2000" connections="100"/>

    <bean id="storeDirectSellDetailRestService" class="com.fionapet.business.facade.StoreDirectSellDetailRestServiceImpl">
        <property name="storeDirectSellDetailService" ref="storeDirectSellDetailService"/>
    </bean>

    <dubbo:reference id="storeDirectSellDetailService" interface="com.fionapet.business.service.StoreDirectSellDetailService"/>
    <!--仓库直销明细 api -->


	<!--返回商品明细 api -->
    <dubbo:service interface="com.fionapet.business.facade.ReturnCommodityDetailRestService" ref="returnCommodityDetailRestService"
                   protocol="rest" validation="true" timeout="2000" connections="100"/>

    <bean id="returnCommodityDetailRestService" class="com.fionapet.business.facade.ReturnCommodityDetailRestServiceImpl">
        <property name="returnCommodityDetailService" ref="returnCommodityDetailService"/>
    </bean>

    <dubbo:reference id="returnCommodityDetailService" interface="com.fionapet.business.service.ReturnCommodityDetailService"/>
    <!--返回商品明细 api -->


	<!--服务主表 api -->
    <dubbo:service interface="com.fionapet.business.facade.ServiceRestService" ref="serviceRestService"
                   protocol="rest" validation="true" timeout="2000" connections="100"/>

    <bean id="serviceRestService" class="com.fionapet.business.facade.ServiceRestServiceImpl">
        <property name="serviceService" ref="serviceService"/>
    </bean>

    <dubbo:reference id="serviceService" interface="com.fionapet.business.service.ServiceService"/>
    <!--服务主表 api -->


	<!--住院处方明细 api -->
    <dubbo:service interface="com.fionapet.business.facade.InHospitalPrescriptionDetailRestService" ref="inHospitalPrescriptionDetailRestService"
                   protocol="rest" validation="true" timeout="2000" connections="100"/>

    <bean id="inHospitalPrescriptionDetailRestService" class="com.fionapet.business.facade.InHospitalPrescriptionDetailRestServiceImpl">
        <property name="inHospitalPrescriptionDetailService" ref="inHospitalPrescriptionDetailService"/>
    </bean>

    <dubbo:reference id="inHospitalPrescriptionDetailService" interface="com.fionapet.business.service.InHospitalPrescriptionDetailService"/>
    <!--住院处方明细 api -->


	<!--住院处方 api -->
    <dubbo:service interface="com.fionapet.business.facade.InHospitalPrescriptionRestService" ref="inHospitalPrescriptionRestService"
                   protocol="rest" validation="true" timeout="2000" connections="100"/>

    <bean id="inHospitalPrescriptionRestService" class="com.fionapet.business.facade.InHospitalPrescriptionRestServiceImpl">
        <property name="inHospitalPrescriptionService" ref="inHospitalPrescriptionService"/>
    </bean>

    <dubbo:reference id="inHospitalPrescriptionService" interface="com.fionapet.business.service.InHospitalPrescriptionService"/>
    <!--住院处方 api -->


	<!--处方明细 api -->
    <dubbo:service interface="com.fionapet.business.facade.BaseMedicPrescriptionDetailRestService" ref="baseMedicPrescriptionDetailRestService"
                   protocol="rest" validation="true" timeout="2000" connections="100"/>

    <bean id="baseMedicPrescriptionDetailRestService" class="com.fionapet.business.facade.BaseMedicPrescriptionDetailRestServiceImpl">
        <property name="baseMedicPrescriptionDetailService" ref="baseMedicPrescriptionDetailService"/>
    </bean>

    <dubbo:reference id="baseMedicPrescriptionDetailService" interface="com.fionapet.business.service.BaseMedicPrescriptionDetailService"/>
    <!--处方明细 api -->


	<!--处方 api -->
    <dubbo:service interface="com.fionapet.business.facade.BaseMedicPrescriptionRestService" ref="baseMedicPrescriptionRestService"
                   protocol="rest" validation="true" timeout="2000" connections="100"/>

    <bean id="baseMedicPrescriptionRestService" class="com.fionapet.business.facade.BaseMedicPrescriptionRestServiceImpl">
        <property name="baseMedicPrescriptionService" ref="baseMedicPrescriptionService"/>
    </bean>

    <dubbo:reference id="baseMedicPrescriptionService" interface="com.fionapet.business.service.BaseMedicPrescriptionService"/>
    <!--处方 api -->


	<!--宠物 api -->
    <dubbo:service interface="com.fionapet.business.facade.PetRestService" ref="petRestService"
                   protocol="rest" validation="true" timeout="2000" connections="100"/>

    <bean id="petRestService" class="com.fionapet.business.facade.PetRestServiceImpl">
        <property name="petService" ref="petService"/>
    </bean>

    <dubbo:reference id="petService" interface="com.fionapet.business.service.PetService"/>
    <!--宠物 api -->

</beans>
